{
  "project_info": {
    "project_number": "667335037561",
    "project_id": "live-notification-708d8",
    "storage_bucket": "live-notification-708d8.firebasestorage.app"
  },
  "client": [
    {
      "client_info": {
        "mobilesdk_app_id": "1:667335037561:android:e3770775dd76dfd2e7baa8",
        "android_client_info": {
          "package_name": "com.frontend"
        }
      },
      "oauth_client": [],
      "api_key": [
        {
          "current_key": "AIzaSyBX8mGbMCU5ZrGkk8ygpFXe2xJ34R6odbo"
        }
      ],
      "services": {
        "appinvite_service": {
          "other_platform_oauth_client": []
        }
      }
    }
  ],
  "configuration_version": "1"
}